jointfinder/__init__.py
jointfinder/jf.py
jointfinder/setup.py
jointfinder/util.py
jointfinder/worker.py
jointfinder/worker_cuda.py
jointfinder/worker_numba.py
jointfinder/worker_numba_line.py
jointfinder-1.1.8.dist-info/METADATA
jointfinder-1.1.8.dist-info/WHEEL
jointfinder-1.1.8.dist-info/top_level.txt
jointfinder-1.1.8.dist-info/RECORD
