Metadata-Version: 2.1
Name: jointfinder
Version: 1.1.8
Summary: Find edge-to-edge and edge-to-surface joints of planar polygons
Home-page: https://github.com/SiDODOL/jointfinder
Author: Dr Z. Y. Tay & J. Hadi
Author-email: januwar.hadi@singaporetech.edu.sg
License: UNKNOWN
Platform: UNKNOWN
Classifier: Programming Language :: Python :: 3
Classifier: License :: OSI Approved :: MIT License
Classifier: Operating System :: OS Independent
Requires-Python: >=3.8.5
Requires-Dist: pandas
Requires-Dist: numpy
Requires-Dist: numba
Requires-Dist: tqdm
Requires-Dist: matplotlib
